pycwatch/__init__.py
pycwatch/client.py
pycwatch/config.py
pycwatch/conversion.py
pycwatch/endpoints.py
pycwatch/exceptions.py
pycwatch/models.py
pycwatch/utils.py
pycwatch-1.1.4.dist-info/LICENSE
pycwatch-1.1.4.dist-info/METADATA
pycwatch-1.1.4.dist-info/WHEEL
pycwatch-1.1.4.dist-info/RECORD
