Metadata-Version: 2.1
Name: pycwatch
Version: 1.1.4
Summary: A client library for the Cryptowatch Rest API.
Home-page: https://github.com/ljnsn/pycwatch
License: MIT
Keywords: cryptocurrency,crypto,prices,cryptowatch
Author: ljnsn
Author-email: 82611987+ljnsn@users.noreply.github.com
Requires-Python: >=3.7,<4.0
Classifier: Development Status :: 5 - Production/Stable
Classifier: Environment :: Web Environment
Classifier: Intended Audience :: Developers
Classifier: License :: OSI Approved :: MIT License
Classifier: Operating System :: OS Independent
Classifier: Programming Language :: Python
Classifier: Programming Language :: Python :: 3
Classifier: Programming Language :: Python :: 3.7
Classifier: Programming Language :: Python :: 3.8
Classifier: Programming Language :: Python :: 3.9
Classifier: Programming Language :: Python :: 3.10
Classifier: Programming Language :: Python :: 3.11
Classifier: Topic :: Internet :: WWW/HTTP :: Dynamic Content
Requires-Dist: api-client (>=1.3.1)
Requires-Dist: attrs (>=23.1.0)
Requires-Dist: cattrs (>=23.1.2)
Requires-Dist: importlib-metadata (<4.3) ; python_version < "3.8"
Requires-Dist: requests (>=2.27.1)
Requires-Dist: typing-extensions (>=4.7.1) ; python_version < "3.10"
Requires-Dist: ujson (>=5.7.0)
Project-URL: Repository, https://github.com/ljnsn/pycwatch
